CHANGELOG.md
LICENSE
README.md
requirements-examples.txt
examples/7color/html/README.md
examples/spectra6/comics/README.md
inky/__init__.py
inky/auto.py
inky/eeprom.py
inky/inky.py
inky/inky_ac073tc1a.py
inky/inky_e673.py
inky/inky_el133uf1.py
inky/inky_jd79661.py
inky/inky_jd79668.py
inky/inky_ssd1608.py
inky/inky_ssd1683.py
inky/inky_uc8159.py
inky/mock.py
inky/phat.py
inky/ssd1608.py
inky/ssd1683.py
inky/what.py
inky-2.2.0.dist-info/METADATA
inky-2.2.0.dist-info/WHEEL
inky-2.2.0.dist-info/licenses/LICENSE
inky-2.2.0.dist-info/RECORD
