Metadata-Version: 2.4
Name: inky
Version: 2.2.0
Summary: Inky pHAT Driver
Project-URL: GitHub, https://www.github.com/pimoroni/inky
Project-URL: Homepage, https://www.pimoroni.com
Author-email: Philip Howard <phil@pimoroni.com>
Maintainer-email: Philip Howard <phil@pimoroni.com>
License: MIT License
License-File: LICENSE
Keywords: Raspberry Pi,e-paper
Classifier: Development Status :: 4 - Beta
Classifier: Intended Audience :: Developers
Classifier: License :: OSI Approved :: MIT License
Classifier: Operating System :: POSIX :: Linux
Classifier: Programming Language :: Python :: 3
Classifier: Programming Language :: Python :: 3 :: Only
Classifier: Programming Language :: Python :: 3.7
Classifier: Programming Language :: Python :: 3.8
Classifier: Programming Language :: Python :: 3.9
Classifier: Programming Language :: Python :: 3.10
Classifier: Programming Language :: Python :: 3.11
Classifier: Topic :: Software Development
Classifier: Topic :: Software Development :: Libraries
Classifier: Topic :: System :: Hardware
Requires-Python: >=3.7
Requires-Dist: gpiodevice>=0.0.3
Requires-Dist: numpy
Requires-Dist: pillow
Requires-Dist: smbus2
Requires-Dist: spidev
Provides-Extra: example-depends
Requires-Dist: beautifulsoup4; extra == 'example-depends'
Requires-Dist: font-fredoka-one; extra == 'example-depends'
Requires-Dist: font-hanken-grotesk; extra == 'example-depends'
Requires-Dist: font-intuitive; extra == 'example-depends'
Requires-Dist: font-source-sans-pro; extra == 'example-depends'
Requires-Dist: font-source-serif-pro; extra == 'example-depends'
Requires-Dist: fonts; extra == 'example-depends'
Requires-Dist: geocoder; extra == 'example-depends'
Requires-Dist: pandas==2.2.3; extra == 'example-depends'
Requires-Dist: pillow; extra == 'example-depends'
Requires-Dist: requests; extra == 'example-depends'
Requires-Dist: seaborn; extra == 'example-depends'
Requires-Dist: wikiquotes; extra == 'example-depends'
